largefish/__init__.py
largefish/largefish.py
largefish-0.6.dist-info/LICENSE
largefish-0.6.dist-info/METADATA
largefish-0.6.dist-info/WHEEL
largefish-0.6.dist-info/top_level.txt
largefish-0.6.dist-info/RECORD
