Metadata-Version: 2.1
Name: largefish
Version: 0.6
Summary: this is a cub
Home-page: 
Author: xzy
Author-email: 1078702704@qq.com
Maintainer: xzy
Maintainer-email: 1078702704@qq.com
License: MIT License
Classifier: Development Status :: 3 - Alpha
Classifier: Intended Audience :: Developers
Classifier: Topic :: Software Development :: Build Tools
Classifier: License :: OSI Approved :: MIT License
Classifier: Programming Language :: Python :: 3
Requires-Python: >=3.9
License-File: LICENSE
